allytools/__init__.py
allytools/py.typed
allytools/array/Crop2D.py
allytools/array/__init__.py
allytools/button/__init__.py
allytools/button/new_buton.py
allytools/core/__init__.py
allytools/core/meta.py
allytools/core/npz.py
allytools/db/__init__.py
allytools/db/frozen_db.py
allytools/db/model_id.py
allytools/dotnet/__init__.py
allytools/dotnet/convert.py
allytools/event/Aggregator.py
allytools/event/BasicEvents.py
allytools/event/EventLogger.py
allytools/event/__init__.py
allytools/files/__init__.py
allytools/files/require.py
allytools/frozen/__init__.py
allytools/frozen/frozen.py
allytools/h5/__init__.py
allytools/h5/aid.py
allytools/h5/attribute_read.py
allytools/h5/attribute_write.py
allytools/h5/dataclass_list_cls.py
allytools/h5/dataclass_list_read.py
allytools/h5/dataclass_list_write.py
allytools/h5/dataclass_read.py
allytools/h5/dataclass_write.py
allytools/h5/h5aid.py
allytools/h5/basic/array_read.py
allytools/h5/basic/array_write.py
allytools/h5/basic/enum_sequence.py
allytools/h5/basic/numeric_1d.py
allytools/h5/basic/string_1d.py
allytools/h5/basic/string_scalar.py
allytools/logger/__init__.py
allytools/logger/configure_log.py
allytools/logger/log_setup.py
allytools/logger/loger_types.py
allytools/signal/__init__.py
allytools/signal/safe_signal.py
allytools/strings/__init__.py
allytools/strings/obj_to_str.py
allytools/strings/strings.py
allytools/time/__init__.py
allytools/time/time.py
allytools/transform/o1.py
allytools/types/__init__.py
allytools/types/coerce_value.py
allytools/types/coercers.py
allytools/types/validate_cast.py
allytools/units/__init__.py
allytools/units/angle.py
allytools/units/angle_unit.py
allytools/units/area.py
allytools/units/area_unit.py
allytools/units/length.py
allytools/units/length_array.py
allytools/units/length_unit.py
allytools/units/percentage.py
allytools/units/quantity.py
allytools/vector/__init__.py
allytools/vector/normalize.py
allytools/win/__init__.py
allytools/win/registry_location.py
allytools-0.6.1.dist-info/licenses/LICENSE
allytools-0.6.1.dist-info/METADATA
allytools-0.6.1.dist-info/WHEEL
allytools-0.6.1.dist-info/top_level.txt
allytools-0.6.1.dist-info/RECORD
