Metadata-Version: 2.4
Name: allytools
Version: 0.6.1
Summary: Utility toolkit
Author-email: Anton Sharapov <sharapov.anton@gmail.com>
License: MIT License
Project-URL: Homepage, https://github.com/SharapovAnton/allytools
Project-URL: Issues, https://github.com/SharapovAnton/allytools/issues
Classifier: Programming Language :: Python :: 3
Classifier: Programming Language :: Python :: 3 :: Only
Classifier: License :: OSI Approved :: MIT License
Classifier: Operating System :: OS Independent
Classifier: Typing :: Typed
Requires-Python: >=3.8
License-File: LICENSE
Requires-Dist: PyQt5
Requires-Dist: numpy>=1.23
Provides-Extra: dev
Requires-Dist: pytest; extra == "dev"
Requires-Dist: mypy; extra == "dev"
Requires-Dist: ruff; extra == "dev"
Provides-Extra: qa
Requires-Dist: tox; extra == "qa"
Requires-Dist: pre-commit; extra == "qa"
Dynamic: license-file
